{
	"info": {
		"_postman_id": "509042df-11e8-4e89-ba70-bd2a4457dec0",
		"name": "Assessment-SDT",
		"schema": "https://schema.getpostman.com/json/collection/v2.1.0/collection.json",
		"_exporter_id": "11802207"
	},
	"item": [
		{
			"name": "Route Index",
			"request": {
				"method": "GET",
				"header": [
					{
						"key": "Content-Type",
						"value": "application/json",
						"type": "text"
					}
				],
				"url": {
					"raw": "http://localhost:8080",
					"protocol": "http",
					"host": [
						"localhost"
					],
					"port": "8080"
				}
			},
			"response": [
				{
					"name": "Route Index",
					"originalRequest": {
						"method": "GET",
						"header": [
							{
								"key": "Content-Type",
								"value": "application/json",
								"type": "text"
							}
						],
						"url": {
							"raw": "http://localhost:8080",
							"protocol": "http",
							"host": [
								"localhost"
							],
							"port": "8080"
						}
					},
					"status": "OK",
					"code": 200,
					"_postman_previewlanguage": "json",
					"header": [
						{
							"key": "X-Powered-By",
							"value": "Express"
						},
						{
							"key": "Access-Control-Allow-Origin",
							"value": "http://localhost:8080"
						},
						{
							"key": "Vary",
							"value": "Origin"
						},
						{
							"key": "Content-Type",
							"value": "application/json; charset=utf-8"
						},
						{
							"key": "Content-Length",
							"value": "56"
						},
						{
							"key": "ETag",
							"value": "W/\"38-KtydoLnojQhUUeS6NE/z5f1HOEc\""
						},
						{
							"key": "Date",
							"value": "Fri, 07 Jul 2023 09:55:45 GMT"
						},
						{
							"key": "Connection",
							"value": "keep-alive"
						},
						{
							"key": "Keep-Alive",
							"value": "timeout=5"
						}
					],
					"cookie": [],
					"body": "{\n    \"message\": \"Welcome to the daily birthday reminder API\"\n}"
				}
			]
		},
		{
			"name": "Post Request -- Success",
			"request": {
				"method": "POST",
				"header": [],
				"body": {
					"mode": "urlencoded",
					"urlencoded": [
						{
							"key": "first_name",
							"value": "rakha",
							"type": "text"
						},
						{
							"key": "last_name",
							"value": "wisesa",
							"type": "text"
						},
						{
							"key": "email",
							"value": "rakha.rozaqtama@gmail.com",
							"type": "text"
						},
						{
							"key": "birthday_date",
							"value": "2020-12-06",
							"type": "text"
						},
						{
							"key": "timezone_location",
							"value": "jakarta",
							"type": "text"
						},
						{
							"key": "",
							"value": "",
							"type": "text",
							"disabled": true
						}
					]
				},
				"url": {
					"raw": "http://localhost:8080/user",
					"protocol": "http",
					"host": [
						"localhost"
					],
					"port": "8080",
					"path": [
						"user"
					]
				}
			},
			"response": [
				{
					"name": "Post Request -- Success",
					"originalRequest": {
						"method": "POST",
						"header": [],
						"body": {
							"mode": "urlencoded",
							"urlencoded": [
								{
									"key": "first_name",
									"value": "rakha",
									"type": "text"
								},
								{
									"key": "last_name",
									"value": "wisesa",
									"type": "text"
								},
								{
									"key": "email",
									"value": "rakha.rozaqtama@gmail.com",
									"type": "text"
								},
								{
									"key": "birthday_date",
									"value": "2020-07-07",
									"type": "text"
								},
								{
									"key": "timezone_location",
									"value": "bangkok",
									"type": "text"
								},
								{
									"key": "",
									"value": "",
									"type": "text",
									"disabled": true
								}
							]
						},
						"url": {
							"raw": "http://localhost:8080/user",
							"protocol": "http",
							"host": [
								"localhost"
							],
							"port": "8080",
							"path": [
								"user"
							]
						}
					},
					"status": "Created",
					"code": 201,
					"_postman_previewlanguage": "json",
					"header": [
						{
							"key": "X-Powered-By",
							"value": "Express"
						},
						{
							"key": "Access-Control-Allow-Origin",
							"value": "http://localhost:8080"
						},
						{
							"key": "Vary",
							"value": "Origin"
						},
						{
							"key": "Content-Type",
							"value": "application/json; charset=utf-8"
						},
						{
							"key": "Content-Length",
							"value": "52"
						},
						{
							"key": "ETag",
							"value": "W/\"34-FlVKIlgrd0r4aFt5cGq+L79LGaQ\""
						},
						{
							"key": "Date",
							"value": "Fri, 07 Jul 2023 09:51:34 GMT"
						},
						{
							"key": "Connection",
							"value": "keep-alive"
						},
						{
							"key": "Keep-Alive",
							"value": "timeout=5"
						}
					],
					"cookie": [],
					"body": "{\n    \"message\": \"Data created and saved on the database\"\n}"
				}
			]
		},
		{
			"name": "Put Request -- Success",
			"request": {
				"method": "PUT",
				"header": [],
				"body": {
					"mode": "urlencoded",
					"urlencoded": [
						{
							"key": "timezone_location",
							"value": "makassar",
							"type": "text"
						}
					]
				},
				"url": {
					"raw": "http://localhost:8080/user/1",
					"protocol": "http",
					"host": [
						"localhost"
					],
					"port": "8080",
					"path": [
						"user",
						"1"
					]
				}
			},
			"response": [
				{
					"name": "Put Request -- Success",
					"originalRequest": {
						"method": "PUT",
						"header": [],
						"body": {
							"mode": "urlencoded",
							"urlencoded": [
								{
									"key": "timezone_location",
									"value": "makassar",
									"type": "text"
								}
							]
						},
						"url": {
							"raw": "http://localhost:8080/user/1",
							"protocol": "http",
							"host": [
								"localhost"
							],
							"port": "8080",
							"path": [
								"user",
								"1"
							]
						}
					},
					"status": "OK",
					"code": 200,
					"_postman_previewlanguage": "json",
					"header": [
						{
							"key": "X-Powered-By",
							"value": "Express"
						},
						{
							"key": "Access-Control-Allow-Origin",
							"value": "http://localhost:8080"
						},
						{
							"key": "Vary",
							"value": "Origin"
						},
						{
							"key": "Content-Type",
							"value": "application/json; charset=utf-8"
						},
						{
							"key": "Content-Length",
							"value": "43"
						},
						{
							"key": "ETag",
							"value": "W/\"2b-v8c/J+LcaDHoTHXXjN1q8ru3t+U\""
						},
						{
							"key": "Date",
							"value": "Fri, 07 Jul 2023 09:56:21 GMT"
						},
						{
							"key": "Connection",
							"value": "keep-alive"
						},
						{
							"key": "Keep-Alive",
							"value": "timeout=5"
						}
					],
					"cookie": [],
					"body": "{\n    \"message\": \"user was updated successfully\"\n}"
				}
			]
		},
		{
			"name": "Delete Request -- Success",
			"request": {
				"method": "DELETE",
				"header": [],
				"url": {
					"raw": "http://localhost:8080/user/1",
					"protocol": "http",
					"host": [
						"localhost"
					],
					"port": "8080",
					"path": [
						"user",
						"1"
					]
				}
			},
			"response": [
				{
					"name": "Delete Request -- Success",
					"originalRequest": {
						"method": "DELETE",
						"header": [],
						"url": {
							"raw": "http://localhost:8080/user/1",
							"protocol": "http",
							"host": [
								"localhost"
							],
							"port": "8080",
							"path": [
								"user",
								"1"
							]
						}
					},
					"status": "OK",
					"code": 200,
					"_postman_previewlanguage": "json",
					"header": [
						{
							"key": "X-Powered-By",
							"value": "Express"
						},
						{
							"key": "Access-Control-Allow-Origin",
							"value": "http://localhost:8080"
						},
						{
							"key": "Vary",
							"value": "Origin"
						},
						{
							"key": "Content-Type",
							"value": "application/json; charset=utf-8"
						},
						{
							"key": "Content-Length",
							"value": "44"
						},
						{
							"key": "ETag",
							"value": "W/\"2c-jn7c46QuDmebfk9aBnXedZIRzAk\""
						},
						{
							"key": "Date",
							"value": "Fri, 07 Jul 2023 09:57:19 GMT"
						},
						{
							"key": "Connection",
							"value": "keep-alive"
						},
						{
							"key": "Keep-Alive",
							"value": "timeout=5"
						}
					],
					"cookie": [],
					"body": "{\n    \"message\": \"User was deleted successfully!\"\n}"
				}
			]
		},
		{
			"name": "Post Request -- Failed",
			"request": {
				"method": "POST",
				"header": [],
				"body": {
					"mode": "urlencoded",
					"urlencoded": [
						{
							"key": "first_name",
							"value": "handoko",
							"type": "text"
						},
						{
							"key": "last_name",
							"value": "joko",
							"type": "text"
						},
						{
							"key": "email",
							"value": "rakha.rozaqtama@gmail.com",
							"type": "text"
						},
						{
							"key": "",
							"value": "",
							"type": "text",
							"disabled": true
						},
						{
							"key": "",
							"value": "",
							"type": "text",
							"disabled": true
						}
					]
				},
				"url": {
					"raw": "http://localhost:8080/user",
					"protocol": "http",
					"host": [
						"localhost"
					],
					"port": "8080",
					"path": [
						"user"
					]
				}
			},
			"response": [
				{
					"name": "Post Request -- Failed",
					"originalRequest": {
						"method": "POST",
						"header": [],
						"body": {
							"mode": "urlencoded",
							"urlencoded": []
						},
						"url": {
							"raw": "http://localhost:8080/user",
							"protocol": "http",
							"host": [
								"localhost"
							],
							"port": "8080",
							"path": [
								"user"
							]
						}
					},
					"status": "Bad Request",
					"code": 400,
					"_postman_previewlanguage": "json",
					"header": [
						{
							"key": "X-Powered-By",
							"value": "Express"
						},
						{
							"key": "Access-Control-Allow-Origin",
							"value": "http://localhost:8080"
						},
						{
							"key": "Vary",
							"value": "Origin"
						},
						{
							"key": "Content-Type",
							"value": "application/json; charset=utf-8"
						},
						{
							"key": "Content-Length",
							"value": "37"
						},
						{
							"key": "ETag",
							"value": "W/\"25-mzSlmY9QmuwETWQQ4VveBPwQcME\""
						},
						{
							"key": "Date",
							"value": "Fri, 07 Jul 2023 09:58:27 GMT"
						},
						{
							"key": "Connection",
							"value": "keep-alive"
						},
						{
							"key": "Keep-Alive",
							"value": "timeout=5"
						}
					],
					"cookie": [],
					"body": "{\n    \"message\": \"Content can't be empty!\"\n}"
				}
			]
		},
		{
			"name": "Put Request -- Failed",
			"request": {
				"method": "PUT",
				"header": [],
				"body": {
					"mode": "urlencoded",
					"urlencoded": [
						{
							"key": "timezone_location",
							"value": "jayapura",
							"type": "text"
						}
					]
				},
				"url": {
					"raw": "http://localhost:8080/user/1",
					"protocol": "http",
					"host": [
						"localhost"
					],
					"port": "8080",
					"path": [
						"user",
						"1"
					]
				}
			},
			"response": [
				{
					"name": "Put Request -- Failed",
					"originalRequest": {
						"method": "PUT",
						"header": [],
						"body": {
							"mode": "urlencoded",
							"urlencoded": [
								{
									"key": "timezone_location",
									"value": "jayapura",
									"type": "text"
								}
							]
						},
						"url": {
							"raw": "http://localhost:8080/user/1",
							"protocol": "http",
							"host": [
								"localhost"
							],
							"port": "8080",
							"path": [
								"user",
								"1"
							]
						}
					},
					"status": "OK",
					"code": 200,
					"_postman_previewlanguage": "json",
					"header": [
						{
							"key": "X-Powered-By",
							"value": "Express"
						},
						{
							"key": "Access-Control-Allow-Origin",
							"value": "http://localhost:8080"
						},
						{
							"key": "Vary",
							"value": "Origin"
						},
						{
							"key": "Content-Type",
							"value": "application/json; charset=utf-8"
						},
						{
							"key": "Content-Length",
							"value": "81"
						},
						{
							"key": "ETag",
							"value": "W/\"51-y/DspS9orulZvKa6a0euLNRsj34\""
						},
						{
							"key": "Date",
							"value": "Fri, 07 Jul 2023 09:59:38 GMT"
						},
						{
							"key": "Connection",
							"value": "keep-alive"
						},
						{
							"key": "Keep-Alive",
							"value": "timeout=5"
						}
					],
					"cookie": [],
					"body": "{\n    \"message\": \"Cannot update user with id = 1, maybe user with id = 1 is not found\"\n}"
				}
			]
		},
		{
			"name": "Delete Request -- Failed",
			"request": {
				"method": "DELETE",
				"header": [],
				"url": {
					"raw": "http://localhost:8080/user/1",
					"protocol": "http",
					"host": [
						"localhost"
					],
					"port": "8080",
					"path": [
						"user",
						"1"
					]
				}
			},
			"response": [
				{
					"name": "Delete Request -- Failed",
					"originalRequest": {
						"method": "DELETE",
						"header": [],
						"url": {
							"raw": "http://localhost:8080/user/1",
							"protocol": "http",
							"host": [
								"localhost"
							],
							"port": "8080",
							"path": [
								"user",
								"1"
							]
						}
					},
					"status": "OK",
					"code": 200,
					"_postman_previewlanguage": "json",
					"header": [
						{
							"key": "X-Powered-By",
							"value": "Express"
						},
						{
							"key": "Access-Control-Allow-Origin",
							"value": "http://localhost:8080"
						},
						{
							"key": "Vary",
							"value": "Origin"
						},
						{
							"key": "Content-Type",
							"value": "application/json; charset=utf-8"
						},
						{
							"key": "Content-Length",
							"value": "79"
						},
						{
							"key": "ETag",
							"value": "W/\"4f-GVHjVs/o6KgvoXUqtW3S5vqKV30\""
						},
						{
							"key": "Date",
							"value": "Fri, 07 Jul 2023 10:06:17 GMT"
						},
						{
							"key": "Connection",
							"value": "keep-alive"
						},
						{
							"key": "Keep-Alive",
							"value": "timeout=5"
						}
					],
					"cookie": [],
					"body": "{\n    \"message\": \"Cannot delete user with id = 1. Maybe user with id = 1 not found!\"\n}"
				}
			]
		}
	]
}